avatarko_picture_getter/__init__.py
avatarko_picture_getter/__main__.py
avatarko_picture_getter/avatarko_picture_getter.py
avatarko_picture_getter/settings.py
avatarko_picture_getter-0.0.2.dist-info/LICENSE
avatarko_picture_getter-0.0.2.dist-info/METADATA
avatarko_picture_getter-0.0.2.dist-info/WHEEL
avatarko_picture_getter-0.0.2.dist-info/top_level.txt
avatarko_picture_getter-0.0.2.dist-info/RECORD
