Metadata-Version: 2.1
Name: avatarko-picture-getter
Version: 0.0.2
Summary: Avatarko picture getter
Home-page: https://github.com/neznakomec16/avatarko_picture_getter
Author: Neznakomec16
Author-email: 
License: UNKNOWN
Platform: UNKNOWN
Classifier: Programming Language :: Python :: 3
Classifier: License :: OSI Approved :: MIT License
Classifier: Operating System :: OS Independent
Requires-Python: >=3.6
Requires-Dist: aiohttp
Requires-Dist: lxml
Requires-Dist: requests
